setup.cfg
setup.py
WPTParser/__init__.py
WPTParser/Constants/RegexConstants.py
WPTParser/Constants/__init__.py
WPTParser/Fetch/__init__.py
WPTParser/JSONParser/DataExtracter.py
WPTParser/JSONParser/KeyDataExtracter.py
WPTParser/JSONParser/ListDataExtracter.py
WPTParser/JSONParser/ListRangeDataExtractor.py
WPTParser/JSONParser/ObjectListDataExtracter.py
WPTParser/JSONParser/ObjectListDataRegexExtracter.py
WPTParser/JSONParser/__init__.py
wpt_parser.egg-info/PKG-INFO
wpt_parser.egg-info/SOURCES.txt
wpt_parser.egg-info/dependency_links.txt
wpt_parser.egg-info/requires.txt
wpt_parser.egg-info/top_level.txt