Metadata-Version: 2.1
Name: wpt-parser
Version: 0.0.5
Summary: A plug-n-play package fetch test data from WPT and parse for specific keys
Home-page: https://github.com/Bharat23/wpt-parser
Author: Bharat Sinha
Author-email: bharat.sinha.2307@gmail.com
License: MIT
Keywords: WPT parser,wpt,speed curve,webpagetest,json
Platform: UNKNOWN
Classifier: Programming Language :: Python :: 3
Classifier: License :: OSI Approved :: MIT License
Classifier: Operating System :: OS Independent
Classifier: Intended Audience :: Developers
Requires-Python: >=3.6
